Metadata-Version: 2.1
Name: electricpower
Version: 0.1.0
Summary:  Measurements of electric power consumption in one household
Home-page: https://github.com/Asmaa-khorkhash/householdelectricpower
Author: Asmaa khorkhash
Author-email: asmaakhorkhash@gmail.com
Classifier: Programming Language :: Python
Classifier: Programming Language :: Python :: 3
Classifier: Programming Language :: Python :: 3.6
